starbase1/__init__.py
starbase1-0.0.0.dist-info/METADATA
starbase1-0.0.0.dist-info/WHEEL
starbase1-0.0.0.dist-info/RECORD
