Metadata-Version: 2.4
Name: starbase1
Version: 0.0.0
Summary: Data-star framework for Python (coming soon)
Author-email: Ryan Funduk <ryan@funduk.ca>
